beetsplug/__init__.py
beetsplug/id3extract.py
beets_id3extract-0.1.0.dist-info/METADATA
beets_id3extract-0.1.0.dist-info/WHEEL
beets_id3extract-0.1.0.dist-info/top_level.txt
beets_id3extract-0.1.0.dist-info/RECORD
