Metadata-Version: 2.1
Name: beets-id3extract
Version: 0.1.0
Summary: Beets plugin to map arbitrary ID3 tags to beets custom fields
Home-page: https://github.com/bcotton/beets-id3extract
Author: Bob Cotton
Author-email: Bob Cotton <bob.cotton@gmail.com>
License: MIT
Project-URL: Homepage, https://github.com/bcotton/beets-id3extract
Project-URL: Repository, https://github.com/bcotton/beets-id3extract.git
Platform: ALL
Classifier: Topic :: Multimedia :: Sound/Audio
Classifier: Topic :: Multimedia :: Sound/Audio :: Players :: MP3
Classifier: License :: OSI Approved :: MIT License
Classifier: Environment :: Console
Classifier: Programming Language :: Python :: 3
Classifier: Programming Language :: Python :: 3.8
Classifier: Programming Language :: Python :: 3.9
Classifier: Programming Language :: Python :: 3.10
Classifier: Programming Language :: Python :: 3.11
Classifier: Programming Language :: Python :: 3.12
Requires-Python: >=3.8
Requires-Dist: beets>=1.6.0
Requires-Dist: mediafile
Requires-Dist: mutagen
